flpc-0.2.5.dist-info/METADATA
flpc-0.2.5.dist-info/WHEEL
flpc-0.2.5.dist-info/license_files/LICENSE
flpc/__init__.py
flpc/__init__.pyi
flpc/py.typed
flpc/flpc.pypy38-pp73-s390x-linux-gnu.so
flpc-0.2.5.dist-info/RECORD
