Metadata-Version: 2.3
Name: flpc
Version: 0.2.5
Classifier: Programming Language :: Rust
Classifier: Programming Language :: Python :: Implementation :: CPython
Classifier: Programming Language :: Python :: Implementation :: PyPy
License-File: LICENSE
Summary: A Lightning Fast ⚡ Rust-based regex crate wrapper for Python3 to get faster performance. 👾
Maintainer-email: Adarsh Gourab Mahalik <gourabmahalikadarsh@gmail.com>
License: MIT
Requires-Python: >=3.8
Project-URL: Homepage, https://github.com/itsmeadarsh2008/flpc
Project-URL: Repository, https://github.com/itsmeadarsh2008/flpc.git
Project-URL: Bug Tracker, https://github.com/itsmeadarsh2008/flpc/issues
